com/__init__.py
com/project/__init__.py
com/project/Logger/Logger.py
com/project/Logger/Logger1.py
com/project/Logger/Logger3.py
com/project/Logger/Logger4.py
com/project/Logger/Logger5.py
com/project/Logger/__init__.py
com/project/Logs/__init__.py
com/project/Logs/logs/__init__.py
com/project/Scrapper/Scrapper.py
com/project/Scrapper/Test.py
com/project/Scrapper/Test1.py
com/project/Scrapper/Test3.py
com/project/Scrapper/Test5.py
com/project/Scrapper/Test6.py
com/project/Scrapper/__init__.py
com/project/common/__init__.py
samplescrap-0.1.0.dist-info/METADATA
samplescrap-0.1.0.dist-info/WHEEL
samplescrap-0.1.0.dist-info/top_level.txt
samplescrap-0.1.0.dist-info/RECORD
