Metadata-Version: 2.1
Name: samplescrap
Version: 0.1.0
Summary: My first Python library
Author: Me
Requires-Dist: beautifulsoup4 ==4.12.3
Requires-Dist: logging ==0.4.9.6
Requires-Dist: setuptools
Requires-Dist: wrapt
Requires-Dist: twine
Requires-Dist: wheel
